Workbook

Sheet Scenario
A1: scenairo_number | B1: Scenario 1 | C1: Scenario 2 | D1: Scenario 3 | E1: Scenario 4 | F1: Scenario 5 | G1: Scenario 6 | H1: Scenario 7 | I1: Scenario 8 | J1: Scenario 9 | K1: Scenario 10 | L1: Scenario 11 | M1: Scenario 12 | N1: Scenario 13 | O1: Scenario 14
A2: scenario_name | B2: =B6 -> default | C2: =C6 -> no-landuse-change | D2: =D6 -> low-uptake | E2: =E6 -> low-tech-change | F2: =F6 -> farm-plan-only | G2: =G6 -> all-profit-farmers | H2: =H6 -> all-enviro-farmers | I2: =I6 -> high-tech-change | ... K2: =K6 -> high-debt | L2: n/a | M2: n/a | N2: n/a | O2: n/a
A3: run-seed | B3: 1 | C3: 1 | D3: 1 | E3: 1 | F3: 1 | G3: 1 | H3: 1 | I3: 1 | J3: 1 | K3: 1
A4: geography-seed | B4: 0 | C4: 0 | D4: 0 | E4: 0 | F4: 0 | G4: 0 | H4: 0 | I4: 0 | J4: 0 | K4: 0
A5: output_data_folder | B5: C:\Users\adam.daigneault\Documents\GitHub\moving-the-middle-abm\data\output | C5: C:\Users\adam.daigneault\Documents\GitHub\moving-the-middle-abm\data\output | D5: C:\Users\adam.daigneault\Documents\GitHub\moving-the-middle-abm\data\output | E5: C:\Users\adam.daigneault\Documents\GitHub\moving-the-middle-abm\data\output | F5: C:\Users\adam.daigneault\Documents\GitHub\moving-the-middle-abm\data\output | G5: C:\Users\adam.daigneault\Documents\GitHub\moving-the-middle-abm\data\output | H5: C:\Users\adam.daigneault\Documents\GitHub\moving-the-middle-abm\data\output | I5: C:\Users\adam.daigneault\Documents\GitHub\moving-the-middle-abm\data\output | J5: C:\Users\adam.daigneault\Documents\GitHub\moving-the-middle-abm\data\output | K5: C:\Users\adam.daigneault\Documents\GitHub\moving-the-middle-abm\data\output
A6: market_data_folder | B6: default | C6: no-landuse-change | D6: low-uptake | E6: low-tech-change | F6: farm-plan-only | G6: all-profit-farmers | H6: all-enviro-farmers | I6: high-tech-change | J6: low-init-intervention | K6: high-debt
A7: spatial_data_folder | B7: C:\Users\adam.daigneault\Documents\GitHub\moving-the-middle-abm\data\spatial\Waihou-Piako | C7: C:\Users\adam.daigneault\Documents\GitHub\moving-the-middle-abm\data\spatial\Waihou-Piako | D7: C:\Users\adam.daigneault\Documents\GitHub\moving-the-middle-abm\data\spatial\Waihou-Piako | E7: C:\Users\adam.daigneault\Documents\GitHub\moving-the-middle-abm\data\spatial\Waihou-Piako | F7: C:\Users\adam.daigneault\Documents\GitHub\moving-the-middle-abm\data\spatial\Waihou-Piako | G7: C:\Users\adam.daigneault\Documents\GitHub\moving-the-middle-abm\data\spatial\Waihou-Piako | H7: C:\Users\adam.daigneault\Documents\GitHub\moving-the-middle-abm\data\spatial\Waihou-Piako | I7: C:\Users\adam.daigneault\Documents\GitHub\moving-the-middle-abm\data\spatial\Waihou-Piako | J7: C:\Users\adam.daigneault\Documents\GitHub\moving-the-middle-abm\data\spatial\Waihou-Piako | K7: C:\Users\adam.daigneault\Documents\GitHub\moving-the-middle-abm\data\spatial\Waihou-Piako
A8: geography_from_files | B8: TRUE | C8: TRUE | D8: TRUE | E8: TRUE | F8: TRUE | G8: TRUE | H8: TRUE | I8: TRUE | J8: TRUE | K8: TRUE
A9: scenario | B9: default | C9: no-landuse-change | D9: low-uptake | E9: low-tech-change | F9: farm-plan-only | G9: all-profit-farmers | H9: all-enviro-farmers | I9: high-tech-change | J9: low-init-intervention | K9: high-debt
A10: region | B10: Waihou-Piako | C10: Waihou-Piako | D10: Waihou-Piako | E10: Waihou-Piako | F10: Waihou-Piako | G10: Waihou-Piako | H10: Waihou-Piako | I10: Waihou-Piako | J10: Waihou-Piako | K10: Waihou-Piako
A11: LUC_aggregation_steps | B11: 0 | C11: 0 | D11: 0 | E11: 0 | F11: 0 | G11: 0 | H11: 0 | I11: 0 | J11: 0 | K11: 0
A12: number_of_farms | B12: 0 | C12: 0 | D12: 0 | E12: 0 | F12: 0 | G12: 0 | H12: 0 | I12: 0 | J12: 0 | K12: 0
A13: correlated_landuse | B13: 0 | C13: 0 | D13: 0 | E13: 0 | F13: 0 | G13: 0 | H13: 0 | I13: 0 | J13: 0 | K13: 0
A14: landuse_aggregation_steps | B14: 0 | C14: 0 | D14: 0 | E14: 0 | F14: 0 | G14: 0 | H14: 0 | I14: 0 | J14: 0 | K14: 0
A15: include_networks | B15: FALSE | C15: FALSE | D15: FALSE | E15: FALSE | F15: FALSE | G15: FALSE | H15: FALSE | I15: FALSE | J15: FALSE | K15: FALSE
A16: n_local_links | B16: 6 | C16: 6 | D16: 6 | E16: 6 | F16: 6 | G16: 6 | H16: 6 | I16: 6 | J16: 6 | K16: 6
A17: n_catchment_links | B17: 6 | C17: 6 | D17: 6 | E17: 6 | F17: 6 | G17: 6 | H17: 6 | I17: 6 | J17: 6 | K17: 6
A18: interest_rate | B18: 3 | C18: 3 | D18: 3 | E18: 3 | F18: 3 | G18: 3 | H18: 3 | I18: 3 | J18: 3 | K18: 10
A19: mortgate_term | B19: 20 | C19: 20 | D19: 20 | E19: 20 | F19: 20 | G19: 20 | H19: 20 | I19: 20 | J19: 20 | K19: 20
A20: nudge_efficacy | B20: 1 | C20: 1 | D20: 1 | E20: 1 | F20: 1 | G20: 1 | H20: 1 | I20: 1 | J20: 1 | K20: 1
A21: landuse_change_on_succession | B21: FALSE | C21: FALSE | D21: FALSE | E21: FALSE | F21: FALSE | G21: FALSE | H21: FALSE | I21: FALSE | J21: FALSE | K21: FALSE
A22: apply_suitability | B22: TRUE | C22: TRUE | D22: TRUE | E22: TRUE | F22: TRUE | G22: TRUE | H22: TRUE | I22: TRUE | J22: TRUE | K22: TRUE

Sheet Estimates
A1: Catchment | B1: Scenario | C1: tick | D1: income_costs_income | E1: income_costs_costs | F1: income_costs_debt | G1: interventions_Build_Wetland | H1: interventions_Clean_Races | I1: interventions_Farm_Plan | J1: interventions_Riparian_Planting | K1: intervention_limits_Build_Wetland | L1: intervention_limits_Clean_Races | M1: intervention_limits_Farm_Plan | N1: intervention_limits_Riparian_Planting | O1: intervention_props_Build_Wetland | P1: intervention_props_Clean_Races | Q1: intervention_props_Farm_Plan | R1: intervention_props_Riparian_Planting | S1: landuse_Crop | T1: landuse_Dairy | U1: landuse_Forest | V1: landuse_SNB | W1: env_metrics_ghg_emissions | X1: env_metrics_nitrates | Y1: env_metrics_sediment | Z1: env_metrics_phosphates | AA1: env_metrics_e_coli | AB1: income_costs_netrev
A2: =Scenario!B10 -> Waihou-Piako | B2: =Scenario!B2 -> default | C2: 0 | D2: 1414664765 | E2: 1196543938 | F2: 413244508 | G2: 1332 | H2: 840 | I2: 1219 | J2: 1267 | K2: 12351 | L2: 9078 | M2: 12167 | N2: 12351 | O2: 0.1078 | P2: 0.0925 | Q2: 0.1002 | R2: 0.1026 | S2: 184 | T2: 9078 | U2: 1068 | V2: 3089 | W2: 1379504.3 | X2: 5738137.5 | Y2: 1133321.2 | Z2: 133573.86 | AA2: 724425.82 | AB2: =D2-E2 -> 218120827
A3: =A2 -> Waihou-Piako | B3: =B2 -> default | C3: 1 | D3: 1414355374 | E3: 1195580426 | F3: 539290032 | G3: 1857 | H3: 1299 | I3: 1744 | J3: 1805 | K3: 11986 | L3: 8732 | M3: 11780 | N3: 11986 | O3: 0.1549 | P3: 0.1488 | Q3: 0.148 | R3: 0.1506 | S3: 206 | T3: 8732 | U3: 1433 | V3: 3048 | W3: 1379442.7 | X3: 5738698.1 | Y3: 1133888.9 | Z3: 133519.22 | AA3: 724125.34 | AB3: =D3-E3 -> 218774948
A4: =A3 -> Waihou-Piako | B4: =B3 -> default | C4: 2 | D4: 1388621652 | E4: 1176412327 | F4: 516275058 | G4: 2300 | H4: 1619 | I4: 2265 | J4: 2329 | K4: 11701 | L4: 8480 | M4: 11448 | N4: 11701 | O4: 0.1966 | P4: 0.1909 | Q4: 0.1979 | R4: 0.199 | S4: 253 | T4: 8480 | U4: 1718 | V4: 2968 | W4: 1232595.2 | X4: 5371382.7 | Y4: 1021632.7 | Z4: 122403.34 | AA4: 646410.77 | AB4: =D4-E4 -> 212209325
A5: =A4 -> Waihou-Piako | B5: =B4 -> default | C5: 3 | D5: 1371598906 | E5: 1165610145 | F5: 435703211 | G5: 2792 | H5: 2053 | I5: 2849 | J5: 2805 | K5: 11456 | L5: 8237 | M5: 11171 | N5: 11456 | O5: 0.2437 | P5: 0.2492 | Q5: 0.255 | R5: 0.2448 | S5: 285 | T5: 8237 | U5: 1963 | V5: 2934 | W5: 1122346.1 | X5: 5077642.8 | Y5: 910980.58 | Z5: 113206.3 | AA5: 584418.83 | AB5: =D5-E5 -> 205988761
A6: =A5 -> Waihou-Piako | B6: =B5 -> default | C6: 4 | D6: 1352155262 | E6: 1151264464 | F6: 392852800 | G6: 3180 | H6: 2387 | I6: 3408 | J6: 3261 | K6: 11270 | L6: 8086 | M6: 10974 | N6: 11270 | O6: 0.2822 | P6: 0.2952 | Q6: 0.3106 | R6: 0.2894 | S6: 296 | T6: 8086 | U6: 2149 | V6: 2888 | W6: 1019124.1 | X6: 4778034.4 | Y6: 813920.61 | Z6: 103720.03 | AA6: 522956.67 | AB6: =D6-E6 -> 200890798
A7: =A6 -> Waihou-Piako | B7: =B6 -> default | C7: 5 | D7: 1342620321 | E7: 1144498439 | F7: 374964916 | G7: 3687 | H7: 2702 | I7: 3931 | J7: 3753 | K7: 11133 | L7: 7954 | M7: 10839 | N7: 11133 | O7: 0.3312 | P7: 0.3397 | Q7: 0.3627 | R7: 0.3371 | S7: 294 | T7: 7954 | U7: 2286 | V7: 2885 | W7: 943355.44 | X7: 4547126.5 | Y7: 738094.83 | Z7: 96836.4 | AA7: 477983.46 | AB7: =D7-E7 -> 198121882
A8: =A7 -> Waihou-Piako | B8: =B7 -> default | C8: 6 | D8: 1329591747 | E8: 1137944185 | F8: 364740154 | G8: 4198 | H8: 2986 | I8: 4305 | J8: 4189 | K8: 10951 | L8: 7778 | M8: 10649 | N8: 10951 | O8: 0.3833 | P8: 0.3839 | Q8: 0.4043 | R8: 0.3825 | S8: 302 | T8: 7778 | U8: 2468 | V8: 2871 | W8: 887153.86 | X8: 4308107.8 | Y8: 665648.98 | Z8: 89467.808 | AA8: 433742.45 | AB8: =D8-E8 -> 191647562
A9: =A8 -> Waihou-Piako | B9: =B8 -> default | C9: 7 | D9: 1312680754 | E9: 1125545689 | F9: 370093649 | G9: 4512 | H9: 3305 | I9: 4675 | J9: 4482 | K9: 10795 | L9: 7632 | M9: 10491 | N9: 10795 | O9: 0.418 | P9: 0.433 | Q9: 0.4456 | R9: 0.4152 | S9: 304 | T9: 7632 | U9: 2624 | V9: 2859 | W9: 805372.56 | X9: 4071737.1 | Y9: 598523.82 | Z9: 82686.496 | AA9: 388602.86 | AB9: =D9-E9 -> 187135065
A10: =A9 -> Waihou-Piako | B10: =B9 -> default | C10: 8 | D10: 1302238124 | E10: 1117826234 | F10: 366746915 | G10: 4921 | H10: 3577 | I10: 4989 | J10: 4866 | K10: 10660 | L10: 7524 | M10: 10363 | N10: 10660 | O10: 0.4616 | P10: 0.4754 | Q10: 0.4814 | R10: 0.4565 | S10: 297 | T10: 7524 | U10: 2759 | V10: 2839 | W10: 745304.75 | X10: 3912447.7 | Y10: 552595.89 | Z10: 78092.784 | AA10: 357283.07 | AB10: =D10-E10 -> 184411890
A11: =A10 -> Waihou-Piako | B11: =B10 -> default | C11: 9 | D11: 1292494805 | E11: 1111216713 | F11: 364069497 | G11: 5218 | H11: 3818 | I11: 5326 | J11: 5075 | K11: 10494 | L11: 7381 | M11: 10189 | N11: 10494 | O11: 0.4972 | P11: 0.5173 | Q11: 0.5227 | R11: 0.4836 | S11: 305 | T11: 7381 | U11: 2925 | V11: 2808 | W11: 691212.05 | X11: 3726600 | Y11: 514233.81 | Z11: 73097.632 | AA11: 326050.86 | AB11: =D11-E11 -> 181278092
A12: =A11 -> Waihou-Piako | B12: =B11 -> default | C12: 10 | D12: 1282157445 | E12: 1103811554 | F12: 357796201 | G12: 5519 | H12: 4043 | I12: 5685 | J12: 5327 | K12: 10354 | L12: 7285 | M12: 10040 | N12: 10354 | O12: 0.533 | P12: 0.555 | Q12: 0.5662 | R12: 0.5145 | S12: 314 | T12: 7285 | U12: 3065 | V12: 2755 | W12: 625571.47 | X12: 3580957.1 | Y12: 483296.13 | Z12: 69351.536 | AA12: 303426.56 | AB12: =D12-E12 -> 178345891
A13: =A12 -> Waihou-Piako | B13: =Scenario!C2 -> no-landuse-change | C13: 0 | D13: 1414664765 | E13: 1196543938 | F13: 413244508 | G13: 1332 | H13: 840 | I13: 1219 | J13: 1267 | K13: 12351 | L13: 9078 | M13: 12167 | N13: 12351 | O13: 0.1078 | P13: 0.0925 | Q13: 0.1002 | R13: 0.1026 | S13: 184 | T13: 9078 | U13: 1068 | V13: 3089 | W13: 1379504.3 | X13: 5738137.5 | Y13: 1133321.2 | Z13: 133573.86 | AA13: 724425.82 | AB13: =D13-E13 -> 218120827
A14: =A13 -> Waihou-Piako | B14: =B13 -> no-landuse-change | C14: 1 | D14: 1414355374 | E14: 1195580426 | F14: 536940147 | G14: 1941 | H14: 1172 | I14: 1923 | J14: 1854 | K14: 12351 | L14: 9078 | M14: 12167 | N14: 12351 | O14: 0.1572 | P14: 0.1291 | Q14: 0.1581 | R14: 0.1501 | S14: 184 | T14: 9078 | U14: 1068 | V14: 3089 | W14: 1379442.7 | X14: 5738698.1 | Y14: 1133888.9 | Z14: 133519.22 | AA14: 724125.34 | AB14: =D14-E14 -> 218774948
A15: =A14 -> Waihou-Piako | B15: =B14 -> no-landuse-change | C15: 2 | D15: 1410369197 | E15: 1196314744 | F15: 517770605 | G15: 2566 | H15: 1593 | I15: 2516 | J15: 2499 | K15: 12351 | L15: 9078 | M15: 12167 | N15: 12351 | O15: 0.2078 | P15: 0.1755 | Q15: 0.2068 | R15: 0.2023 | S15: 184 | T15: 9078 | U15: 1068 | V15: 3089 | W15: 1367148.8 | X15: 5561784 | Y15: 1004919.1 | Z15: 125040.67 | AA15: 667592.26 | AB15: =D15-E15 -> 214054453
A16: =A15 -> Waihou-Piako | B16: =B15 -> no-landuse-change | C16: 3 | D16: 1406305686 | E16: 1196783663 | F16: 473057366 | G16: 3243 | H16: 2005 | I16: 3146 | J16: 3038 | K16: 12351 | L16: 9078 | M16: 12167 | N16: 12351 | O16: 0.2626 | P16: 0.2209 | Q16: 0.2586 | R16: 0.246 | S16: 184 | T16: 9078 | U16: 1068 | V16: 3089 | W16: 1354394.8 | X16: 5354652.3 | Y16: 889758.26 | Z16: 116355.52 | AA16: 610442.78 | AB16: =D16-E16 -> 209522023
A17: =A16 -> Waihou-Piako | B17: =B16 -> no-landuse-change | C17: 4 | D17: 1402000135 | E17: 1196623380 | F17: 438342584 | G17: 3826 | H17: 2400 | I17: 3764 | J17: 3604 | K17: 12351 | L17: 9078 | M17: 12167 | N17: 12351 | O17: 0.3098 | P17: 0.2644 | Q17: 0.3094 | R17: 0.2918 | S17: 184 | T17: 9078 | U17: 1068 | V17: 3089 | W17: 1341486.8 | X17: 5170557.6 | Y17: 795226.8 | Z17: 108322.13 | AA17: 559349.36 | AB17: =D17-E17 -> 205376755
A18: =A17 -> Waihou-Piako | B18: =B17 -> no-landuse-change | C18: 5 | D18: 1400591435 | E18: 1197077131 | F18: 392532844 | G18: 4353 | H18: 2972 | I18: 4306 | J18: 4115 | K18: 12351 | L18: 9078 | M18: 12167 | N18: 12351 | O18: 0.3524 | P18: 0.3274 | Q18: 0.3539 | R18: 0.3332 | S18: 184 | T18: 9078 | U18: 1068 | V18: 3089 | W18: 1329725.3 | X18: 4989080.1 | Y18: 705336.69 | Z18: 101554.32 | AA18: 515503.17 | AB18: =D18-E18 -> 203514304
A19: =A18 -> Waihou-Piako | B19: =B18 -> no-landuse-change | C19: 6 | D19: 1396089949 | E19: 1197739477 | F19: 403608080 | G19: 4950 | H19: 3326 | I19: 4867 | J19: 4604 | K19: 12351 | L19: 9078 | M19: 12167 | N19: 12351 | O19: 0.4008 | P19: 0.3664 | Q19: 0.4 | R19: 0.3728 | S19: 184 | T19: 9078 | U19: 1068 | V19: 3089 | W19: 1323381.8 | X19: 4825034.8 | Y19: 636046.19 | Z19: 95088.544 | AA19: 471360.8 | AB19: =D19-E19 -> 198350472
A20: =A19 -> Waihou-Piako | B20: =B19 -> no-landuse-change | C20: 7 | D20: 1393250787 | E20: 1197403841 | F20: 410049848 | G20: 5343 | H20: 3656 | I20: 5389 | J20: 5012 | K20: 12351 | L20: 9078 | M20: 12167 | N20: 12351 | O20: 0.4326 | P20: 0.4027 | Q20: 0.4429 | R20: 0.4058 | S20: 184 | T20: 9078 | U20: 1068 | V20: 3089 | W20: 1310079.2 | X20: 4664597.8 | Y20: 565463.6 | Z20: 89001.136 | AA20: 433904.82 | AB20: =D20-E20 -> 195846946
A21: =A20 -> Waihou-Piako | B21: =B20 -> no-landuse-change | C21: 8 | D21: 1391423752 | E21: 1197494504 | F21: 379786464 | G21: 5849 | H21: 3973 | I21: 5965 | J21: 5448 | K21: 12351 | L21: 9078 | M21: 12167 | N21: 12351 | O21: 0.4736 | P21: 0.4377 | Q21: 0.4903 | R21: 0.4411 | S21: 184 | T21: 9078 | U21: 1068 | V21: 3089 | W21: 1302645.4 | X21: 4552543 | Y21: 519727.41 | Z21: 84647.136 | AA21: 405919.52 | AB21: =D21-E21 -> 193929248
A22: =A21 -> Waihou-Piako | B22: =B21 -> no-landuse-change | C22: 9 | D22: 1388112081 | E22: 1196856501 | F22: 375749440 | G22: 6180 | H22: 4316 | I22: 6674 | J22: 5916 | K22: 12351 | L22: 9078 | M22: 12167 | N22: 12351 | O22: 0.5004 | P22: 0.4754 | Q22: 0.5485 | R22: 0.479 | S22: 184 | T22: 9078 | U22: 1068 | V22: 3089 | W22: 1292043.6 | X22: 4414408.9 | Y22: 465896.51 | Z22: 79699.104 | AA22: 375574.77 | AB22: =D22-E22 -> 191255580
A23: =A22 -> Waihou-Piako | B23: =B22 -> no-landuse-change | C23: 10 | D23: 1385439615 | E23: 1196595248 | F23: 408307573 | G23: 6556 | H23: 4604 | I23: 7105 | J23: 6296 | K23: 12351 | L23: 9078 | M23: 12167 | N23: 12351 | O23: 0.5308 | P23: 0.5072 | Q23: 0.584 | R23: 0.5098 | S23: 184 | T23: 9078 | U23: 1068 | V23: 3089 | W23: 1285793.7 | X23: 4292131.4 | Y23: 408541.1 | Z23: 75557.472 | AA23: 350834.27 | AB23: =D23-E23 -> 188844367
A24: =A23 -> Waihou-Piako | B24: =Scenario!D2 -> low-uptake | C24: 0 | D24: 1414664765 | E24: 1196543938 | F24: 413244508 | G24: 1332 | H24: 840 | I24: 1219 | J24: 1267 | K24: 12351 | L24: 9078 | M24: 12167 | N24: 12351 | O24: 0.1078 | P24: 0.0925 | Q24: 0.1002 | R24: 0.1026 | S24: 184 | T24: 9078 | U24: 1068 | V24: 3089 | W24: 1379504.3 | X24: 5738137.5 | Y24: 1133321.2 | Z24: 133573.86 | AA24: 724425.82 | AB24: =D24-E24 -> 218120827
A25: =A24 -> Waihou-Piako | B25: =B24 -> low-uptake | C25: 1 | D25: 1414355374 | E25: 1195580426 | F25: 560348737 | G25: 1533 | H25: 983 | I25: 1398 | J25: 1443 | K25: 12194 | L25: 8941 | M25: 12007 | N25: 12194 | O25: 0.1257 | P25: 0.1099 | Q25: 0.1164 | R25: 0.1183 | S25: 187 | T25: 8941 | U25: 1225 | V25: 3066 | W25: 1379442.7 | X25: 5738698.1 | Y25: 1133888.9 | Z25: 133519.22 | AA25: 724125.34 | AB25: =D25-E25 -> 218774948
A26: =A25 -> Waihou-Piako | B26: =B25 -> low-uptake | C26: 2 | D26: 1405022734 | E26: 1188948964 | F26: 544045213 | G26: 1745 | H26: 1124 | I26: 1591 | J26: 1634 | K26: 12030 | L26: 8788 | M26: 11830 | N26: 12030 | O26: 0.1451 | P26: 0.1279 | Q26: 0.1345 | R26: 0.1358 | S26: 200 | T26: 8788 | U26: 1389 | V26: 3042 | W26: 1318198.5 | X26: 5604322.5 | Y26: 1090810.2 | Z26: 129350.34 | AA26: 695826.53 | AB26: =D26-E26 -> 216073770
A27: =A26 -> Waihou-Piako | B27: =B26 -> low-uptake | C27: 3 | D27: 1394058213 | E27: 1181752817 | F27: 524108733 | G27: 1896 | H27: 1240 | I27: 1774 | J27: 1764 | K27: 11853 | L27: 8643 | M27: 11639 | N27: 11853 | O27: 0.16 | P27: 0.1435 | Q27: 0.1524 | R27: 0.1488 | S27: 214 | T27: 8643 | U27: 1566 | V27: 2996 | W27: 1256047.2 | X27: 5452569.8 | Y27: 1041359.3 | Z27: 125067.89 | AA27: 664463.52 | AB27: =D27-E27 -> 212305396
A28: =A27 -> Waihou-Piako | B28: =B27 -> low-uptake | C28: 4 | D28: 1386398241 | E28: 1174718645 | F28: 469381980 | G28: 2086 | H28: 1355 | I28: 1990 | J28: 1939 | K28: 11762 | L28: 8564 | M28: 11538 | N28: 11762 | O28: 0.1774 | P28: 0.1582 | Q28: 0.1725 | R28: 0.1649 | S28: 224 | T28: 8564 | U28: 1657 | V28: 2974 | W28: 1188589.3 | X28: 5326176.8 | Y28: 997150.14 | Z28: 121202.05 | AA28: 638524.48 | AB28: =D28-E28 -> 211679596
A29: =A28 -> Waihou-Piako | B29: =B28 -> low-uptake | C29: 5 | D29: 1378930400 | E29: 1169861189 | F29: 416380375 | G29: 2229 | H29: 1504 | I29: 2218 | J29: 2120 | K29: 11661 | L29: 8445 | M29: 11431 | N29: 11661 | O29: 0.1911 | P29: 0.1781 | Q29: 0.194 | R29: 0.1818 | S29: 230 | T29: 8445 | U29: 1758 | V29: 2986 | W29: 1153623.3 | X29: 5221564.9 | Y29: 959089.62 | Z29: 117846.26 | AA29: 616187.68 | AB29: =D29-E29 -> 209069211
A30: =A29 -> Waihou-Piako | B30: =B29 -> low-uptake | C30: 6 | D30: 1369090377 | E30: 1162110428 | F30: 410131844 | G30: 2426 | H30: 1629 | I30: 2467 | J30: 2312 | K30: 11514 | L30: 8300 | M30: 11277 | N30: 11514 | O30: 0.2107 | P30: 0.1963 | Q30: 0.2188 | R30: 0.2008 | S30: 237 | T30: 8300 | U30: 1905 | V30: 2977 | W30: 1107929.9 | X30: 5109773.4 | Y30: 919724.03 | Z30: 114682.06 | AA30: 593233.01 | AB30: =D30-E30 -> 206979949
A31: =A30 -> Waihou-Piako | B31: =B30 -> low-uptake | C31: 7 | D31: 1357772881 | E31: 1154322191 | F31: 413244130 | G31: 2586 | H31: 1755 | I31: 2607 | J31: 2492 | K31: 11438 | L31: 8213 | M31: 11184 | N31: 11438 | O31: 0.2261 | P31: 0.2137 | Q31: 0.2331 | R31: 0.2179 | S31: 254 | T31: 8213 | U31: 1981 | V31: 2971 | W31: 1046842.9 | X31: 4972523.9 | Y31: 872408.38 | Z31: 110667.68 | AA31: 565699.92 | AB31: =D31-E31 -> 203450690
A32: =A31 -> Waihou-Piako | B32: =B31 -> low-uptake | C32: 8 | D32: 1350909361 | E32: 1148825818 | F32: 431057134 | G32: 2764 | H32: 1847 | I32: 2771 | J32: 2691 | K32: 11354 | L32: 8078 | M32: 11074 | N32: 11354 | O32: 0.2434 | P32: 0.2286 | Q32: 0.2502 | R32: 0.237 | S32: 280 | T32: 8078 | U32: 2065 | V32: 2996 | W32: 1017113.5 | X32: 4884861.8 | Y32: 839703.63 | Z32: 107869.01 | AA32: 547268.05 | AB32: =D32-E32 -> 202083543
A33: =A32 -> Waihou-Piako | B33: =B32 -> low-uptake | C33: 9 | D33: 1339104579 | E33: 1138871314 | F33: 409636864 | G33: 2915 | H33: 1969 | I33: 2925 | J33: 2860 | K33: 11224 | L33: 7984 | M33: 10933 | N33: 11224 | O33: 0.2597 | P33: 0.2466 | Q33: 0.2675 | R33: 0.2548 | S33: 291 | T33: 7984 | U33: 2195 | V33: 2949 | W33: 973686.61 | X33: 4751813.7 | Y33: 811552.72 | Z33: 104218.38 | AA33: 524390.05 | AB33: =D33-E33 -> 200233265
A34: =A33 -> Waihou-Piako | B34: =B33 -> low-uptake | C34: 10 | D34: 1331830243 | E34: 1133958567 | F34: 419009405 | G34: 3062 | H34: 2115 | I34: 3099 | J34: 3041 | K34: 11178 | L34: 7931 | M34: 10878 | N34: 11178 | O34: 0.2739 | P34: 0.2667 | Q34: 0.2849 | R34: 0.2721 | S34: 300 | T34: 7931 | U34: 2241 | V34: 2947 | W34: 928033.41 | X34: 4640285.7 | Y34: 785326.88 | Z34: 101168.85 | AA34: 504572.77 | AB34: =D34-E34 -> 197871676
A35: =A34 -> Waihou-Piako | B35: =Scenario!E2 -> low-tech-change | C35: 0 | D35: 1414664765 | E35: 1196543938 | F35: 413244508 | G35: 1332 | H35: 840 | I35: 1219 | J35: 1267 | K35: 12351 | L35: 9078 | M35: 12167 | N35: 12351 | O35: 0.1078 | P35: 0.0925 | Q35: 0.1002 | R35: 0.1026 | S35: 184 | T35: 9078 | U35: 1068 | V35: 3089 | W35: 1379504.3 | X35: 5738137.5 | Y35: 1133321.2 | Z35: 133573.86 | AA35: 724425.82 | AB35: =D35-E35 -> 218120827
A36: =A35 -> Waihou-Piako | B36: =B35 -> low-tech-change | C36: 1 | D36: 1414355374 | E36: 1195580426 | F36: 539290032 | G36: 1857 | H36: 1299 | I36: 1744 | J36: 1805 | K36: 11986 | L36: 8732 | M36: 11780 | N36: 11986 | O36: 0.1549 | P36: 0.1488 | Q36: 0.148 | R36: 0.1506 | S36: 206 | T36: 8732 | U36: 1433 | V36: 3048 | W36: 1379442.7 | X36: 5738698.1 | Y36: 1133888.9 | Z36: 133519.22 | AA36: 724125.34 | AB36: =D36-E36 -> 218774948
A37: =A36 -> Waihou-Piako | B37: =B36 -> low-tech-change | C37: 2 | D37: 1249731688 | E37: 1176412327 | F37: 368040856 | G37: 2355 | H37: 1568 | I37: 2189 | J37: 2233 | K37: 11723 | L37: 8530 | M37: 11519 | N37: 11723 | O37: 0.2009 | P37: 0.1838 | Q37: 0.19 | R37: 0.1905 | S37: 204 | T37: 8530 | U37: 1696 | V37: 2989 | W37: 1232595.2 | X37: 5371382.7 | Y37: 1021632.7 | Z37: 122403.34 | AA37: 646410.77 | AB37: =D37-E37 -> 73319361
A38: =A37 -> Waihou-Piako | B38: =B37 -> low-tech-change | C38: 3 | D38: 1236678093 | E38: 1167502437 | F38: 268722386 | G38: 2808 | H38: 1839 | I38: 2534 | J38: 2563 | K38: 11243 | L38: 8159 | M38: 11027 | N38: 11243 | O38: 0.2498 | P38: 0.2254 | Q38: 0.2298 | R38: 0.228 | S38: 216 | T38: 8159 | U38: 2176 | V38: 2868 | W38: 1134521.5 | X38: 5104942.6 | Y38: 928105.68 | Z38: 113993.9 | AA38: 589045.98 | AB38: =D38-E38 -> 69175656
A39: =A38 -> Waihou-Piako | B39: =B38 -> low-tech-change | C39: 4 | D39: 1215573501 | E39: 1149478228 | F39: 191482186 | G39: 3258 | H39: 2118 | I39: 2979 | J39: 3009 | K39: 10925 | L39: 7903 | M39: 10683 | N39: 10925 | O39: 0.2982 | P39: 0.268 | Q39: 0.2789 | R39: 0.2754 | S39: 242 | T39: 7903 | U39: 2494 | V39: 2780 | W39: 960019.55 | X39: 4769657 | Y39: 832134.46 | Z39: 104856.51 | AA39: 525622.45 | AB39: =D39-E39 -> 66095273
A40: =A39 -> Waihou-Piako | B40: =B39 -> low-tech-change | C40: 5 | D40: 1200582478 | E40: 1138781608 | F40: 151907575 | G40: 3632 | H40: 2424 | I40: 3551 | J40: 3437 | K40: 10757 | L40: 7770 | M40: 10501 | N40: 10757 | O40: 0.3376 | P40: 0.312 | Q40: 0.3382 | R40: 0.3195 | S40: 256 | T40: 7770 | U40: 2662 | V40: 2731 | W40: 839892.24 | X40: 4474977.1 | Y40: 745728.32 | Z40: 96126.992 | AA40: 469869.89 | AB40: =D40-E40 -> 61800870
A41: =A40 -> Waihou-Piako | B41: =B40 -> low-tech-change | C41: 6 | D41: 1192197940 | E41: 1130765560 | F41: 137250694 | G41: 3957 | H41: 2658 | I41: 4024 | J41: 3807 | K41: 10525 | L41: 7555 | M41: 10234 | N41: 10525 | O41: 0.376 | P41: 0.3518 | Q41: 0.3932 | R41: 0.3617 | S41: 291 | T41: 7555 | U41: 2894 | V41: 2679 | W41: 772404.62 | X41: 4262482.8 | Y41: 662461.47 | Z41: 90062.112 | AA41: 429500.13 | AB41: =D41-E41 -> 61432380
A42: =A41 -> Waihou-Piako | B42: =B41 -> low-tech-change | C42: 7 | D42: 1178729374 | E42: 1122186366 | F42: 152664828 | G42: 4299 | H42: 2930 | I42: 4419 | J42: 4185 | K42: 10369 | L42: 7423 | M42: 10064 | N42: 10369 | O42: 0.4146 | P42: 0.3947 | Q42: 0.4391 | R42: 0.4036 | S42: 305 | T42: 7423 | U42: 3050 | V42: 2641 | W42: 679687.14 | X42: 4030112.2 | Y42: 597765.82 | Z42: 83436.048 | AA42: 387936.38 | AB42: =D42-E42 -> 56543008
A43: =A42 -> Waihou-Piako | B43: =B42 -> low-tech-change | C43: 8 | D43: 1171117580 | E43: 1116030513 | F43: 148273044 | G43: 4610 | H43: 3126 | I43: 4670 | J43: 4611 | K43: 10230 | L43: 7306 | M43: 9911 | N43: 10230 | O43: 0.4506 | P43: 0.4279 | Q43: 0.4712 | R43: 0.4507 | S43: 319 | T43: 7306 | U43: 3189 | V43: 2605 | W43: 618902.18 | X43: 3853484.7 | Y43: 539523.55 | Z43: 78195.072 | AA43: 352942.29 | AB43: =D43-E43 -> 55087067
A44: =A43 -> Waihou-Piako | B44: =B43 -> low-tech-change | C44: 9 | D44: 1162971879 | E44: 1109662085 | F44: 158592891 | G44: 4813 | H44: 3381 | I44: 4893 | J44: 4864 | K44: 10013 | L44: 7120 | M44: 9694 | N44: 10013 | O44: 0.4807 | P44: 0.4749 | Q44: 0.5047 | R44: 0.4858 | S44: 319 | T44: 7120 | U44: 3406 | V44: 2574 | W44: 563646.82 | X44: 3668722.5 | Y44: 496882.59 | Z44: 73292.48 | AA44: 321105.63 | AB44: =D44-E44 -> 53309794
A45: =A44 -> Waihou-Piako | B45: =B44 -> low-tech-change | C45: 10 | D45: 1152349232 | E45: 1101431128 | F45: 162253466 | G45: 5221 | H45: 3580 | I45: 5054 | J45: 5152 | K45: 9832 | L45: 6972 | M45: 9504 | N45: 9832 | O45: 0.531 | P45: 0.5135 | Q45: 0.5318 | R45: 0.524 | S45: 328 | T45: 6972 | U45: 3587 | V45: 2532 | W45: 484916.42 | X45: 3487141.3 | Y45: 475326.34 | Z45: 69415.312 | AA45: 296310.69 | AB45: =D45-E45 -> 50918104
A46: =A45 -> Waihou-Piako | B46: =Scenario!F2 -> farm-plan-only | C46: 0 | D46: 1414664765 | E46: 1196543938 | F46: 413244508 | G46: 1332 | H46: 840 | I46: 1219 | J46: 1267 | K46: 12351 | L46: 9078 | M46: 12167 | N46: 12351 | O46: 0.1078 | P46: 0.0925 | Q46: 0.1002 | R46: 0.1026 | S46: 184 | T46: 9078 | U46: 1068 | V46: 3089 | W46: 1379504.3 | X46: 5738137.5 | Y46: 1133321.2 | Z46: 133573.86 | AA46: 724425.82 | AB46: =D46-E46 -> 218120827
A47: =A46 -> Waihou-Piako | B47: =B46 -> farm-plan-only | C47: 1 | D47: 1414355374 | E47: 1195580426 | F47: 562628432 | G47: 1286 | H47: 811 | I47: 1744 | J47: 1256 | K47: 11986 | L47: 8732 | M47: 11780 | N47: 11986 | O47: 0.1073 | P47: 0.0929 | Q47: 0.148 | R47: 0.1048 | S47: 206 | T47: 8732 | U47: 1433 | V47: 3048 | W47: 1379442.7 | X47: 5738698.1 | Y47: 1133888.9 | Z47: 133519.22 | AA47: 724125.34 | AB47: =D47-E47 -> 218774948
A48: =A47 -> Waihou-Piako | B48: =B47 -> farm-plan-only | C48: 2 | D48: 1390915587 | E48: 1177015933 | F48: 555603543 | G48: 1263 | H48: 767 | I48: 2284 | J48: 1218 | K48: 11624 | L48: 8408 | M48: 11402 | N48: 11624 | O48: 0.1087 | P48: 0.0912 | Q48: 0.2003 | R48: 0.1048 | S48: 222 | T48: 8408 | U48: 1795 | V48: 2994 | W48: 1243408.8 | X48: 5547521.5 | Y48: 1090110.4 | Z48: 129110.14 | AA48: 699435.39 | AB48: =D48-E48 -> 213899654
A49: =A48 -> Waihou-Piako | B49: =B48 -> farm-plan-only | C49: 3 | D49: 1369601736 | E49: 1159092763 | F49: 525130408 | G49: 1230 | H49: 751 | I49: 2852 | J49: 1197 | K49: 11363 | L49: 8135 | M49: 11121 | N49: 11363 | O49: 0.1082 | P49: 0.0923 | Q49: 0.2565 | R49: 0.1053 | S49: 242 | T49: 8135 | U49: 2056 | V49: 2986 | W49: 1107960.7 | X49: 5369738.4 | Y49: 1045423.2 | Z49: 124905.15 | AA49: 676959.2 | AB49: =D49-E49 -> 210508973
A50: =A49 -> Waihou-Piako | B50: =B49 -> farm-plan-only | C50: 4 | D50: 1351406449 | E50: 1143518699 | F50: 458747408 | G50: 1201 | H50: 743 | I50: 3376 | J50: 1151 | K50: 11083 | L50: 7951 | M50: 10827 | N50: 11083 | O50: 0.1084 | P50: 0.0934 | Q50: 0.3118 | R50: 0.1039 | S50: 256 | T50: 7951 | U50: 2336 | V50: 2876 | W50: 1003403 | X50: 5225686.5 | Y50: 995383.87 | Z50: 121082 | AA50: 658094.14 | AB50: =D50-E50 -> 207887750
A51: =A50 -> Waihou-Piako | B51: =B50 -> farm-plan-only | C51: 5 | D51: 1342563381 | E51: 1135681008 | F51: 424041503 | G51: 1160 | H51: 713 | I51: 3825 | J51: 1149 | K51: 10942 | L51: 7830 | M51: 10656 | N51: 10942 | O51: 0.106 | P51: 0.0911 | Q51: 0.359 | R51: 0.105 | S51: 286 | T51: 7830 | U51: 2477 | V51: 2826 | W51: 903656.27 | X51: 5115974.8 | Y51: 941181.66 | Z51: 118104.58 | AA51: 639024.3 | AB51: =D51-E51 -> 206882373
A52: =A51 -> Waihou-Piako | B52: =B51 -> farm-plan-only | C52: 6 | D52: 1334959662 | E52: 1131531268 | F52: 431604170 | G52: 1138 | H52: 683 | I52: 4162 | J52: 1130 | K52: 10710 | L52: 7678 | M52: 10442 | N52: 10710 | O52: 0.1063 | P52: 0.089 | Q52: 0.3986 | R52: 0.1055 | S52: 268 | T52: 7678 | U52: 2709 | V52: 2764 | W52: 856034.78 | X52: 5052633.7 | Y52: 898419.63 | Z52: 115911.28 | AA52: 628223.95 | AB52: =D52-E52 -> 203428394
A53: =A52 -> Waihou-Piako | B53: =B52 -> farm-plan-only | C53: 7 | D53: 1326141750 | E53: 1122631766 | F53: 422322635 | G53: 1134 | H53: 670 | I53: 4413 | J53: 1113 | K53: 10574 | L53: 7511 | M53: 10272 | N53: 10574 | O53: 0.1072 | P53: 0.0892 | Q53: 0.4296 | R53: 0.1053 | S53: 302 | T53: 7511 | U53: 2845 | V53: 2761 | W53: 771334.66 | X53: 4958374.8 | Y53: 865363.78 | Z53: 113576.21 | AA53: 615195.15 | AB53: =D53-E53 -> 203509984
A54: =A53 -> Waihou-Piako | B54: =B53 -> farm-plan-only | C54: 8 | D54: 1314150388 | E54: 1112712804 | F54: 415746819 | G54: 1111 | H54: 663 | I54: 4720 | J54: 1073 | K54: 10426 | L54: 7338 | M54: 10092 | N54: 10426 | O54: 0.1066 | P54: 0.0904 | Q54: 0.4677 | R54: 0.1029 | S54: 334 | T54: 7338 | U54: 2993 | V54: 2754 | W54: 715915.66 | X54: 4879633.7 | Y54: 839265.38 | Z54: 111557.36 | AA54: 604974.98 | AB54: =D54-E54 -> 201437584
A55: =A54 -> Waihou-Piako | B55: =B54 -> farm-plan-only | C55: 9 | D55: 1302792439 | E55: 1102132359 | F55: 394408716 | G55: 1097 | H55: 653 | I55: 4933 | J55: 1037 | K55: 10231 | L55: 7102 | M55: 9858 | N55: 10231 | O55: 0.1072 | P55: 0.0919 | Q55: 0.5004 | R55: 0.1014 | S55: 373 | T55: 7102 | U55: 3188 | V55: 2756 | W55: 657093.1 | X55: 4800049.2 | Y55: 816063.36 | Z55: 109681.78 | AA55: 592861.65 | AB55: =D55-E55 -> 200660080
A56: =A55 -> Waihou-Piako | B56: =B55 -> farm-plan-only | C56: 10 | D56: 1284836826 | E56: 1087285476 | F56: 396047667 | G56: 1073 | H56: 635 | I56: 5148 | J56: 1034 | K56: 10060 | L56: 6991 | M56: 9675 | N56: 10060 | O56: 0.1067 | P56: 0.0908 | Q56: 0.5321 | R56: 0.1028 | S56: 385 | T56: 6991 | U56: 3359 | V56: 2684 | W56: 580118.06 | X56: 4699209.5 | Y56: 801400.37 | Z56: 107314.21 | AA56: 579644.91 | AB56: =D56-E56 -> 197551350
A57: =A56 -> Waihou-Piako | B57: =Scenario!G2 -> all-profit-farmers | C57: 0 | D57: 1414664765 | E57: 1196543938 | F57: 413244508 | G57: 1332 | H57: 840 | I57: 1219 | J57: 1267 | K57: 12351 | L57: 9078 | M57: 12167 | N57: 12351 | O57: 0.1078 | P57: 0.0925 | Q57: 0.1002 | R57: 0.1026 | S57: 184 | T57: 9078 | U57: 1068 | V57: 3089 | W57: 1379504.3 | X57: 5738137.5 | Y57: 1133321.2 | Z57: 133573.86 | AA57: 724425.82 | AB57: =D57-E57 -> 218120827
A58: =A57 -> Waihou-Piako | B58: =B57 -> all-profit-farmers | C58: 1 | D58: 1414355374 | E58: 1195580426 | F58: 543151623 | G58: 1758 | H58: 1263 | I58: 1651 | J58: 1746 | K58: 11986 | L58: 8732 | M58: 11780 | N58: 11986 | O58: 0.1467 | P58: 0.1446 | Q58: 0.1402 | R58: 0.1457 | S58: 206 | T58: 8732 | U58: 1433 | V58: 3048 | W58: 1379442.7 | X58: 5738698.1 | Y58: 1133888.9 | Z58: 133519.22 | AA58: 724125.34 | AB58: =D58-E58 -> 218774948
A59: =A58 -> Waihou-Piako | B59: =B58 -> all-profit-farmers | C59: 2 | D59: 1389007200 | E59: 1176464310 | F59: 521062944 | G59: 2334 | H59: 1571 | I59: 2204 | J59: 2152 | K59: 11702 | L59: 8431 | M59: 11462 | N59: 11702 | O59: 0.1995 | P59: 0.1863 | Q59: 0.1923 | R59: 0.1839 | S59: 240 | T59: 8431 | U59: 1717 | V59: 3031 | W59: 1236302.2 | X59: 5390719.3 | Y59: 1037272.8 | Z59: 123488.42 | AA59: 652778.66 | AB59: =D59-E59 -> 212542890
A60: =A59 -> Waihou-Piako | B60: =B59 -> all-profit-farmers | C60: 3 | D60: 1365028283 | E60: 1159364255 | F60: 453163136 | G60: 2808 | H60: 1925 | I60: 2687 | J60: 2546 | K60: 11459 | L60: 8237 | M60: 11203 | N60: 11459 | O60: 0.245 | P60: 0.2337 | Q60: 0.2398 | R60: 0.2222 | S60: 256 | T60: 8237 | U60: 1960 | V60: 2966 | W60: 1116589.5 | X60: 5088712.1 | Y60: 935016.21 | Z60: 113914.05 | AA60: 589529.25 | AB60: =D60-E60 -> 205664028
A61: =A60 -> Waihou-Piako | B61: =B60 -> all-profit-farmers | C61: 4 | D61: 1350541181 | E61: 1148922067 | F61: 405165436 | G61: 3172 | H61: 2245 | I61: 3110 | J61: 2977 | K61: 11287 | L61: 8018 | M61: 11003 | N61: 11287 | O61: 0.281 | P61: 0.28 | Q61: 0.2827 | R61: 0.2638 | S61: 284 | T61: 8018 | U61: 2132 | V61: 2985 | W61: 1019234.8 | X61: 4846405.4 | Y61: 837834.38 | Z61: 105948.08 | AA61: 533922.26 | AB61: =D61-E61 -> 201619114
A62: =A61 -> Waihou-Piako | B62: =B61 -> all-profit-farmers | C62: 5 | D62: 1332254399 | E62: 1134835272 | F62: 383914387 | G62: 3562 | H62: 2509 | I62: 3427 | J62: 3329 | K62: 11056 | L62: 7821 | M62: 10758 | N62: 11056 | O62: 0.3222 | P62: 0.3208 | Q62: 0.3186 | R62: 0.3011 | S62: 298 | T62: 7821 | U62: 2363 | V62: 2937 | W62: 941269.7 | X62: 4601666.8 | Y62: 770666.91 | Z62: 99005.984 | AA62: 488600.67 | AB62: =D62-E62 -> 197419127
A63: =A62 -> Waihou-Piako | B63: =B62 -> all-profit-farmers | C63: 6 | D63: 1318593975 | E63: 1124946904 | F63: 365419894 | G63: 3854 | H63: 2704 | I63: 3869 | J63: 3673 | K63: 10897 | L63: 7685 | M63: 10575 | N63: 10897 | O63: 0.3537 | P63: 0.3519 | Q63: 0.3659 | R63: 0.3371 | S63: 322 | T63: 7685 | U63: 2522 | V63: 2890 | W63: 852324.5 | X63: 4375992.8 | Y63: 712583.3 | Z63: 92762.608 | AA63: 445400.77 | AB63: =D63-E63 -> 193647071
A64: =A63 -> Waihou-Piako | B64: =B63 -> all-profit-farmers | C64: 7 | D64: 1307207058 | E64: 1117930092 | F64: 367059600 | G64: 4119 | H64: 2930 | I64: 4206 | J64: 3993 | K64: 10728 | L64: 7504 | M64: 10388 | N64: 10728 | O64: 0.3839 | P64: 0.3905 | Q64: 0.4049 | R64: 0.3722 | S64: 340 | T64: 7504 | U64: 2691 | V64: 2884 | W64: 786825.82 | X64: 4189261.5 | Y64: 645375.82 | Z64: 87201.488 | AA64: 411491.02 | AB64: =D64-E64 -> 189276966
A65: =A64 -> Waihou-Piako | B65: =B64 -> all-profit-farmers | C65: 8 | D65: 1293276477 | E65: 1106560859 | F65: 396780048 | G65: 4424 | H65: 3052 | I65: 4578 | J65: 4350 | K65: 10587 | L65: 7366 | M65: 10235 | N65: 10587 | O65: 0.4179 | P65: 0.4143 | Q65: 0.4473 | R65: 0.4109 | S65: 352 | T65: 7366 | U65: 2832 | V65: 2869 | W65: 716993.46 | X65: 4007790.5 | Y65: 599105.58 | Z65: 82581.456 | AA65: 382134.22 | AB65: =D65-E65 -> 186715618
A66: =A65 -> Waihou-Piako | B66: =B65 -> all-profit-farmers | C66: 9 | D66: 1282346896 | E66: 1099652152 | F66: 405853068 | G66: 4620 | H66: 3208 | I66: 4822 | J66: 4614 | K66: 10361 | L66: 7186 | M66: 9990 | N66: 10361 | O66: 0.4459 | P66: 0.4464 | Q66: 0.4827 | R66: 0.4453 | S66: 371 | T66: 7186 | U66: 3058 | V66: 2804 | W66: 658835.73 | X66: 3841019.9 | Y66: 549144.75 | Z66: 77685.968 | AA66: 352924.96 | AB66: =D66-E66 -> 182694744
A67: =A66 -> Waihou-Piako | B67: =B66 -> all-profit-farmers | C67: 10 | D67: 1271084613 | E67: 1090421511 | F67: 382298461 | G67: 4813 | H67: 3400 | I67: 5072 | J67: 4929 | K67: 10157 | L67: 7046 | M67: 9781 | N67: 10157 | O67: 0.4739 | P67: 0.4825 | Q67: 0.5186 | R67: 0.4853 | S67: 376 | T67: 7046 | U67: 3262 | V67: 2735 | W67: 572735.02 | X67: 3659363.1 | Y67: 515324.96 | Z67: 73603.616 | AA67: 326201.22 | AB67: =D67-E67 -> 180663102
A68: =A67 -> Waihou-Piako | B68: =Scenario!H2 -> all-enviro-farmers | C68: 0 | D68: 1414664765 | E68: 1196543938 | F68: 413244508 | G68: 1332 | H68: 840 | I68: 1219 | J68: 1267 | K68: 12351 | L68: 9078 | M68: 12167 | N68: 12351 | O68: 0.1078 | P68: 0.0925 | Q68: 0.1002 | R68: 0.1026 | S68: 184 | T68: 9078 | U68: 1068 | V68: 3089 | W68: 1379504.3 | X68: 5738137.5 | Y68: 1133321.2 | Z68: 133573.86 | AA68: 724425.82 | AB68: =D68-E68 -> 218120827
A69: =A68 -> Waihou-Piako | B69: =B68 -> all-enviro-farmers | C69: 1 | D69: 1414355374 | E69: 1195580426 | F69: 517710883 | G69: 2249 | H69: 1579 | I69: 2345 | J69: 2125 | K69: 11986 | L69: 8732 | M69: 11780 | N69: 11986 | O69: 0.1876 | P69: 0.1808 | Q69: 0.1991 | R69: 0.1773 | S69: 206 | T69: 8732 | U69: 1433 | V69: 3048 | W69: 1379442.7 | X69: 5738698.1 | Y69: 1133888.9 | Z69: 133519.22 | AA69: 724125.34 | AB69: =D69-E69 -> 218774948
A70: =A69 -> Waihou-Piako | B70: =B69 -> all-enviro-farmers | C70: 2 | D70: 1386718202 | E70: 1176641041 | F70: 481453846 | G70: 3073 | H70: 2170 | I70: 3243 | J70: 2879 | K70: 11678 | L70: 8455 | M70: 11429 | N70: 11678 | O70: 0.2631 | P70: 0.2567 | Q70: 0.2838 | R70: 0.2465 | S70: 249 | T70: 8455 | U70: 1741 | V70: 2974 | W70: 1225231.1 | X70: 5267833.2 | Y70: 937693.95 | Z70: 117140.02 | AA70: 610379.89 | AB70: =D70-E70 -> 210077161
A71: =A70 -> Waihou-Piako | B71: =B70 -> all-enviro-farmers | C71: 3 | D71: 1365438462 | E71: 1163056449 | F71: 425822184 | G71: 3878 | H71: 2685 | I71: 4253 | J71: 3669 | K71: 11438 | L71: 8279 | M71: 11189 | N71: 11438 | O71: 0.339 | P71: 0.3243 | Q71: 0.3801 | R71: 0.3208 | S71: 249 | T71: 8279 | U71: 1981 | V71: 2910 | W71: 1097751.7 | X71: 4885459.6 | Y71: 774632.18 | Z71: 104094.35 | AA71: 521889.25 | AB71: =D71-E71 -> 202382013
A72: =A71 -> Waihou-Piako | B72: =B71 -> all-enviro-farmers | C72: 4 | D72: 1350413046 | E72: 1155003237 | F72: 380486787 | G72: 4642 | H72: 3180 | I72: 5068 | J72: 4551 | K72: 11236 | L72: 8125 | M72: 10986 | N72: 11236 | O72: 0.4131 | P72: 0.3914 | Q72: 0.4613 | R72: 0.405 | S72: 250 | T72: 8125 | U72: 2183 | V72: 2861 | W72: 999510.22 | X72: 4523296.6 | Y72: 614393.82 | Z72: 91656.176 | AA72: 443191.49 | AB72: =D72-E72 -> 195409809
A73: =A72 -> Waihou-Piako | B73: =B72 -> all-enviro-farmers | C73: 5 | D73: 1336620948 | E73: 1147176535 | F73: 355030441 | G73: 5365 | H73: 3672 | I73: 5572 | J73: 5149 | K73: 11034 | L73: 7947 | M73: 10780 | N73: 11034 | O73: 0.4862 | P73: 0.4621 | Q73: 0.5169 | R73: 0.4666 | S73: 254 | T73: 7947 | U73: 2385 | V73: 2833 | W73: 911472.82 | X73: 4160129.6 | Y73: 502240.11 | Z73: 80533.968 | AA73: 374103.25 | AB73: =D73-E73 -> 189444413
A74: =A73 -> Waihou-Piako | B74: =B73 -> all-enviro-farmers | C74: 6 | D74: 1320471636 | E74: 1139545972 | F74: 371057439 | G74: 5873 | H74: 4086 | I74: 6369 | J74: 5635 | K74: 10877 | L74: 7800 | M74: 10605 | N74: 10877 | O74: 0.5399 | P74: 0.5238 | Q74: 0.6006 | R74: 0.5181 | S74: 272 | T74: 7800 | U74: 2542 | V74: 2805 | W74: 831964.96 | X74: 3865147.7 | Y74: 436686.66 | Z74: 72098.672 | AA74: 322631.14 | AB74: =D74-E74 -> 180925664
A75: =A74 -> Waihou-Piako | B75: =B74 -> all-enviro-farmers | C75: 7 | D75: 1307406558 | E75: 1130336401 | F75: 378760354 | G75: 6420 | H75: 4488 | I75: 6780 | J75: 6183 | K75: 10627 | L75: 7575 | M75: 10332 | N75: 10627 | O75: 0.6041 | P75: 0.5925 | Q75: 0.6562 | R75: 0.5818 | S75: 295 | T75: 7575 | U75: 2792 | V75: 2757 | W75: 758212.05 | X75: 3634450.7 | Y75: 384976.42 | Z75: 65591.024 | AA75: 284609.65 | AB75: =D75-E75 -> 177070157
A76: =A75 -> Waihou-Piako | B76: =B75 -> all-enviro-farmers | C76: 8 | D76: 1291305827 | E76: 1118742832 | F76: 365764952 | G76: 6699 | H76: 4756 | I76: 7248 | J76: 6665 | K76: 10476 | L76: 7420 | M76: 10174 | N76: 10476 | O76: 0.6395 | P76: 0.641 | Q76: 0.7124 | R76: 0.6362 | S76: 302 | T76: 7420 | U76: 2943 | V76: 2754 | W76: 661491.94 | X76: 3355730.2 | Y76: 343081.07 | Z76: 59245.28 | AA76: 243286.5 | AB76: =D76-E76 -> 172562995
A77: =A76 -> Waihou-Piako | B77: =B76 -> all-enviro-farmers | C77: 9 | D77: 1279045783 | E77: 1109819484 | F77: 356175952 | G77: 7034 | H77: 5020 | I77: 7586 | J77: 7022 | K77: 10291 | L77: 7264 | M77: 9998 | N77: 10291 | O77: 0.6835 | P77: 0.6911 | Q77: 0.7588 | R77: 0.6823 | S77: 293 | T77: 7264 | U77: 3128 | V77: 2734 | W77: 594712.22 | X77: 3145556.6 | Y77: 320851.89 | Z77: 54701.76 | AA77: 219485.36 | AB77: =D77-E77 -> 169226299
A78: =A77 -> Waihou-Piako | B78: =B77 -> all-enviro-farmers | C78: 10 | D78: 1266487359 | E78: 1100689749 | F78: 366881214 | G78: 7387 | H78: 5327 | I78: 7760 | J78: 7253 | K78: 10154 | L78: 7127 | M78: 9859 | N78: 10154 | O78: 0.7275 | P78: 0.7474 | Q78: 0.7871 | R78: 0.7143 | S78: 295 | T78: 7127 | U78: 3265 | V78: 2732 | W78: 525871.98 | X78: 2960370.4 | Y78: 299744.32 | Z78: 51059.68 | AA78: 198028.64 | AB78: =D78-E78 -> 165797610
A79: =A78 -> Waihou-Piako | B79: =Scenario!I2 -> high-tech-change | C79: 0 | D79: 1414664765 | E79: 1196543938 | F79: 413244508 | G79: 1332 | H79: 840 | I79: 1219 | J79: 1267 | K79: 12351 | L79: 9078 | M79: 12167 | N79: 12351 | O79: 0.1078 | P79: 0.0925 | Q79: 0.1002 | R79: 0.1026 | S79: 184 | T79: 9078 | U79: 1068 | V79: 3089 | W79: 1379504.3 | X79: 5738137.5 | Y79: 1133321.2 | Z79: 133573.86 | AA79: 724425.82 | AB79: =D79-E79 -> 218120827
A80: =A79 -> Waihou-Piako | B80: =B79 -> high-tech-change | C80: 1 | D80: 1414355374 | E80: 1195580426 | F80: 539290032 | G80: 1857 | H80: 1299 | I80: 1744 | J80: 1805 | K80: 11986 | L80: 8732 | M80: 11780 | N80: 11986 | O80: 0.1549 | P80: 0.1488 | Q80: 0.148 | R80: 0.1506 | S80: 206 | T80: 8732 | U80: 1433 | V80: 3048 | W80: 1379442.7 | X80: 5738698.1 | Y80: 1133888.9 | Z80: 133519.22 | AA80: 724125.34 | AB80: =D80-E80 -> 218774948
A81: =A80 -> Waihou-Piako | B81: =B80 -> high-tech-change | C81: 2 | D81: 1458016601 | E81: 1176412327 | F81: 556806389 | G81: 2522 | H81: 1752 | I81: 2462 | J81: 2468 | K81: 11871 | L81: 8518 | M81: 11645 | N81: 11871 | O81: 0.2125 | P81: 0.2057 | Q81: 0.2114 | R81: 0.2079 | S81: 226 | T81: 8518 | U81: 1548 | V81: 3127 | W81: 1232595.2 | X81: 5371382.7 | Y81: 1021632.7 | Z81: 122403.34 | AA81: 646410.77 | AB81: =D81-E81 -> 281604274
A82: =A81 -> Waihou-Piako | B82: =B81 -> high-tech-change | C82: 3 | D82: 1434788654 | E82: 1162438388 | F82: 567786579 | G82: 3035 | H82: 2062 | I82: 3027 | J82: 2926 | K82: 11616 | L82: 8271 | M82: 11368 | N82: 11616 | O82: 0.2613 | P82: 0.2493 | Q82: 0.2663 | R82: 0.2519 | S82: 248 | T82: 8271 | U82: 1803 | V82: 3097 | W82: 1164119.1 | X82: 5055740 | Y82: 905655.28 | Z82: 111711.31 | AA82: 577607.62 | AB82: =D82-E82 -> 272350266
A83: =A82 -> Waihou-Piako | B83: =B82 -> high-tech-change | C83: 4 | D83: 1416589798 | E83: 1148955578 | F83: 504227139 | G83: 3473 | H83: 2406 | I83: 3490 | J83: 3448 | K83: 11405 | L83: 8106 | M83: 11142 | N83: 11405 | O83: 0.3045 | P83: 0.2968 | Q83: 0.3132 | R83: 0.3023 | S83: 263 | T83: 8106 | U83: 2014 | V83: 3036 | W83: 1062449.8 | X83: 4786971.9 | Y83: 799629.95 | Z83: 102926.7 | AA83: 519423.92 | AB83: =D83-E83 -> 267634220
A84: =A83 -> Waihou-Piako | B84: =B83 -> high-tech-change | C84: 5 | D84: 1403535370 | E84: 1141572338 | F84: 473864019 | G84: 3927 | H84: 2745 | I84: 3960 | J84: 3829 | K84: 11195 | L84: 7924 | M84: 10918 | N84: 11195 | O84: 0.3508 | P84: 0.3464 | Q84: 0.3627 | R84: 0.342 | S84: 277 | T84: 7924 | U84: 2224 | V84: 2994 | W84: 975790.94 | X84: 4531315.4 | Y84: 715055.18 | Z84: 95349.872 | AA84: 469279.6 | AB84: =D84-E84 -> 261963032
A85: =A84 -> Waihou-Piako | B85: =B84 -> high-tech-change | C85: 6 | D85: 1388570968 | E85: 1130966168 | F85: 462211047 | G85: 4376 | H85: 3028 | I85: 4370 | J85: 4326 | K85: 10949 | L85: 7720 | M85: 10666 | N85: 10949 | O85: 0.3997 | P85: 0.3922 | Q85: 0.4097 | R85: 0.3951 | S85: 283 | T85: 7720 | U85: 2470 | V85: 2946 | W85: 892580.58 | X85: 4312003.9 | Y85: 654187.15 | Z85: 88951.872 | AA85: 426727.46 | AB85: =D85-E85 -> 257604800
A86: =A85 -> Waihou-Piako | B86: =B85 -> high-tech-change | C86: 7 | D86: 1372941109 | E86: 1121884328 | F86: 498894101 | G86: 4704 | H86: 3267 | I86: 4858 | J86: 4790 | K86: 10780 | L86: 7543 | M86: 10467 | N86: 10780 | O86: 0.4364 | P86: 0.4331 | Q86: 0.4641 | R86: 0.4443 | S86: 313 | T86: 7543 | U86: 2639 | V86: 2924 | W86: 797010.24 | X86: 4029478.7 | Y86: 584272.48 | Z86: 81432.832 | AA86: 380078.5 | AB86: =D86-E86 -> 251056781
A87: =A86 -> Waihou-Piako | B87: =B86 -> high-tech-change | C87: 8 | D87: 1358865564 | E87: 1112232487 | F87: 478584586 | G87: 5113 | H87: 3461 | I87: 5213 | J87: 5183 | K87: 10591 | L87: 7399 | M87: 10259 | N87: 10591 | O87: 0.4828 | P87: 0.4678 | Q87: 0.5081 | R87: 0.4894 | S87: 332 | T87: 7399 | U87: 2828 | V87: 2860 | W87: 727653.15 | X87: 3824545.4 | Y87: 530387.28 | Z87: 75913.248 | AA87: 344835.09 | AB87: =D87-E87 -> 246633077
A88: =A87 -> Waihou-Piako | B88: =B87 -> high-tech-change | C88: 9 | D88: 1348746077 | E88: 1105239095 | F88: 486234818 | G88: 5359 | H88: 3673 | I88: 5536 | J88: 5422 | K88: 10475 | L88: 7286 | M88: 10131 | N88: 10475 | O88: 0.5116 | P88: 0.5041 | Q88: 0.5464 | R88: 0.5176 | S88: 344 | T88: 7286 | U88: 2944 | V88: 2845 | W88: 654441.95 | X88: 3636583.1 | Y88: 465090 | Z88: 70611.408 | AA88: 310417.62 | AB88: =D88-E88 -> 243506982
A89: =A88 -> Waihou-Piako | B89: =B88 -> high-tech-change | C89: 10 | D89: 1338991678 | E89: 1097919214 | F89: 495243915 | G89: 5534 | H89: 3935 | I89: 5777 | J89: 5685 | K89: 10307 | L89: 7126 | M89: 9978 | N89: 10307 | O89: 0.5369 | P89: 0.5522 | Q89: 0.579 | R89: 0.5516 | S89: 329 | T89: 7126 | U89: 3112 | V89: 2852 | W89: 607010.61 | X89: 3502770.4 | Y89: 449769.06 | Z89: 67274.128 | AA89: 291664.22 | AB89: =D89-E89 -> 241072464
A90: =A89 -> Waihou-Piako | B90: =Scenario!J2 -> low-init-intervention | C90: 0 | D90: 1420128412 | E90: 1196293021 | F90: 434758145 | G90: 398 | H90: 301 | I90: 427 | J90: 424 | K90: 12351 | L90: 9078 | M90: 12167 | N90: 12351 | O90: 0.0322 | P90: 0.0332 | Q90: 0.0351 | R90: 0.0343 | S90: 184 | T90: 9078 | U90: 1068 | V90: 3089 | W90: 1396309.5 | X90: 6020486 | Y90: 1311862.5 | Z90: 146604.13 | AA90: 813662.08 | AB90: =D90-E90 -> 223835391
A91: =A90 -> Waihou-Piako | B91: =B90 -> low-init-intervention | C91: 1 | D91: 1419823939 | E91: 1195330084 | F91: 554645051 | G91: 846 | H91: 760 | I91: 1029 | J91: 1030 | K91: 11922 | L91: 8698 | M91: 11725 | N91: 11922 | O91: 0.071 | P91: 0.0874 | Q91: 0.0878 | R91: 0.0864 | S91: 197 | T91: 8698 | U91: 1497 | V91: 3027 | W91: 1396305.4 | X91: 6021924.5 | Y91: 1312340.5 | Z91: 146541.22 | AA91: 813317.41 | AB91: =D91-E91 -> 224493855
A92: =A91 -> Waihou-Piako | B92: =B91 -> low-init-intervention | C92: 2 | D92: 1391301020 | E92: 1175036253 | F92: 513874409 | G92: 1410 | H92: 1163 | I92: 1645 | J92: 1620 | K92: 11600 | L92: 8396 | M92: 11385 | N92: 11600 | O92: 0.1216 | P92: 0.1385 | Q92: 0.1445 | R92: 0.1397 | S92: 215 | T92: 8396 | U92: 1819 | V92: 2989 | W92: 1229435 | X92: 5611301.9 | Y92: 1177004.4 | Z92: 134266.62 | AA92: 728879.65 | AB92: =D92-E92 -> 216264767
A93: =A92 -> Waihou-Piako | B93: =B92 -> low-init-intervention | C93: 3 | D93: 1367754043 | E93: 1158532802 | F93: 449738018 | G93: 1920 | H93: 1500 | I93: 2248 | J93: 2125 | K93: 11345 | L93: 8208 | M93: 11112 | N93: 11345 | O93: 0.1692 | P93: 0.1827 | Q93: 0.2023 | R93: 0.1873 | S93: 233 | T93: 8208 | U93: 2074 | V93: 2904 | W93: 1097386 | X93: 5245459.8 | Y93: 1045450.6 | Z93: 122658.21 | AA93: 649787.71 | AB93: =D93-E93 -> 209221241
A94: =A93 -> Waihou-Piako | B94: =B93 -> low-init-intervention | C94: 4 | D94: 1355958119 | E94: 1149707871 | F94: 372526482 | G94: 2386 | H94: 1799 | I94: 2833 | J94: 2706 | K94: 11136 | L94: 8076 | M94: 10877 | N94: 11136 | O94: 0.2143 | P94: 0.2228 | Q94: 0.2605 | R94: 0.243 | S94: 259 | T94: 8076 | U94: 2283 | V94: 2801 | W94: 999124.21 | X94: 4970752.3 | Y94: 914361.62 | Z94: 113274.56 | AA94: 583589.01 | AB94: =D94-E94 -> 206250248
A95: =A94 -> Waihou-Piako | B95: =B94 -> low-init-intervention | C95: 5 | D95: 1349492286 | E95: 1146341744 | F95: 359681109 | G95: 2760 | H95: 2171 | I95: 3262 | J95: 3113 | K95: 10968 | L95: 7909 | M95: 10695 | N95: 10968 | O95: 0.2516 | P95: 0.2745 | Q95: 0.305 | R95: 0.2838 | S95: 273 | T95: 7909 | U95: 2451 | V95: 2786 | W95: 920156 | X95: 4696218 | Y95: 807432.66 | Z95: 104195.17 | AA95: 524293.23 | AB95: =D95-E95 -> 203150542
A96: =A95 -> Waihou-Piako | B96: =B95 -> low-init-intervention | C96: 6 | D96: 1337037177 | E96: 1138388719 | F96: 349211098 | G96: 3159 | H96: 2589 | I96: 3648 | J96: 3623 | K96: 10780 | L96: 7746 | M96: 10502 | N96: 10780 | O96: 0.293 | P96: 0.3342 | Q96: 0.3474 | R96: 0.3361 | S96: 278 | T96: 7746 | U96: 2639 | V96: 2756 | W96: 850773.06 | X96: 4476370.4 | Y96: 743854.53 | Z96: 97539.68 | AA96: 479993.14 | AB96: =D96-E96 -> 198648458
A97: =A96 -> Waihou-Piako | B97: =B96 -> low-init-intervention | C97: 7 | D97: 1323436705 | E97: 1129932724 | F97: 367556412 | G97: 3633 | H97: 2872 | I97: 4023 | J97: 3918 | K97: 10549 | L97: 7567 | M97: 10283 | N97: 10549 | O97: 0.3444 | P97: 0.3795 | Q97: 0.3912 | R97: 0.3714 | S97: 266 | T97: 7567 | U97: 2870 | V97: 2716 | W97: 774307.92 | X97: 4237261.8 | Y97: 655977.63 | Z97: 90389.312 | AA97: 432697.02 | AB97: =D97-E97 -> 193503981
A98: =A97 -> Waihou-Piako | B98: =B97 -> low-init-intervention | C98: 8 | D98: 1308919734 | E98: 1119884897 | F98: 387460122 | G98: 4032 | H98: 3081 | I98: 4416 | J98: 4224 | K98: 10379 | L98: 7406 | M98: 10098 | N98: 10379 | O98: 0.3885 | P98: 0.416 | Q98: 0.4373 | R98: 0.407 | S98: 281 | T98: 7406 | U98: 3040 | V98: 2692 | W98: 686746.03 | X98: 4029570.3 | Y98: 602409.73 | Z98: 84271.472 | AA98: 391614.99 | AB98: =D98-E98 -> 189034837
A99: =A98 -> Waihou-Piako | B99: =B98 -> low-init-intervention | C99: 9 | D99: 1297466811 | E99: 1111186155 | F99: 396337243 | G99: 4328 | H99: 3259 | I99: 4715 | J99: 4496 | K99: 10182 | L99: 7225 | M99: 9894 | N99: 10182 | O99: 0.4251 | P99: 0.4511 | Q99: 0.4766 | R99: 0.4416 | S99: 288 | T99: 7225 | U99: 3237 | V99: 2669 | W99: 615222.74 | X99: 3845562 | Y99: 549166.75 | Z99: 78624.032 | AA99: 357156.19 | AB99: =D99-E99 -> 186280656
A100: =A99 -> Waihou-Piako | B100: =B99 -> low-init-intervention | C100: 10 | D100: 1282617395 | E100: 1100895938 | F100: 377979084 | G100: 4570 | H100: 3407 | I100: 5096 | J100: 4719 | K100: 10032 | L100: 7075 | M100: 9725 | N100: 10032 | O100: 0.4555 | P100: 0.4816 | Q100: 0.524 | R100: 0.4704 | S100: 307 | T100: 7075 | U100: 3387 | V100: 2650 | W100: 538126.35 | X100: 3666015.3 | Y100: 514087.98 | Z100: 74118.448 | AA100: 329637.76 | AB100: =D100-E100 -> 181721457
...

Sheet Pivot
A3: Sum of env_metrics_ghg_emissions | B3: Column Labels
A4: Row Labels | B4: default | C4: no-landuse-change | D4: low-uptake | E4: low-tech-change | F4: farm-plan-only | G4: all-profit-farmers | H4: all-enviro-farmers | I4: high-tech-change | J4: low-init-intervention | K4: high-debt | L4: Grand Total
A5: 0 | B5: 1379504.3 | C5: 1379504.3 | D5: 1379504.3 | E5: 1379504.3 | F5: 1379504.3 | G5: 1379504.3 | H5: 1379504.3 | I5: 1379504.3 | J5: 1396309.5 | K5: 1379504.3 | L5: 13811848
A6: 1 | B6: 1379442.7 | C6: 1379442.7 | D6: 1379442.7 | E6: 1379442.7 | F6: 1379442.7 | G6: 1379442.7 | H6: 1379442.7 | I6: 1379442.7 | J6: 1396305.4 | K6: 1379442.7 | L6: 13811290
A7: 2 | B7: 1232595.2 | C7: 1367148.8 | D7: 1318198.5 | E7: 1232595.2 | F7: 1243408.8 | G7: 1236302.2 | H7: 1225231.1 | I7: 1232595.2 | J7: 1229435 | K7: 1224353.2 | L7: 12541863
A8: 3 | B8: 1122346.1 | C8: 1354394.8 | D8: 1256047.2 | E8: 1134521.5 | F8: 1107960.7 | G8: 1116589.5 | H8: 1097751.7 | I8: 1164119.1 | J8: 1097386 | K8: 1038216.5 | L8: 11489333
A9: 4 | B9: 1019124.1 | C9: 1341486.8 | D9: 1188589.3 | E9: 960019.55 | F9: 1003403 | G9: 1019234.8 | H9: 999510.22 | I9: 1062449.8 | J9: 999124.21 | K9: 943415.02 | L9: 10536357
A10: 5 | B10: 943355.44 | C10: 1329725.3 | D10: 1153623.3 | E10: 839892.24 | F10: 903656.27 | G10: 941269.7 | H10: 911472.82 | I10: 975790.94 | J10: 920156 | K10: 848928.78 | L10: 9767870.7
A11: 6 | B11: 887153.86 | C11: 1323381.8 | D11: 1107929.9 | E11: 772404.62 | F11: 856034.78 | G11: 852324.5 | H11: 831964.96 | I11: 892580.58 | J11: 850773.06 | K11: 774876.18 | L11: 9149424.3
A12: 7 | B12: 805372.56 | C12: 1310079.2 | D12: 1046842.9 | E12: 679687.14 | F12: 771334.66 | G12: 786825.82 | H12: 758212.05 | I12: 797010.24 | J12: 774307.92 | K12: 698896.14 | L12: 8428568.7
A13: 8 | B13: 745304.75 | C13: 1302645.4 | D13: 1017113.5 | E13: 618902.18 | F13: 715915.66 | G13: 716993.46 | H13: 661491.94 | I13: 727653.15 | J13: 686746.03 | K13: 629958.05 | L13: 7822724.1
A14: 9 | B14: 691212.05 | C14: 1292043.6 | D14: 973686.61 | E14: 563646.82 | F14: 657093.1 | G14: 658835.73 | H14: 594712.22 | I14: 654441.95 | J14: 615222.74 | K14: 557103.14 | L14: 7257998
A15: 10 | B15: 625571.47 | C15: 1285793.7 | D15: 928033.41 | E15: 484916.42 | F15: 580118.06 | G15: 572735.02 | H15: 525871.98 | I15: 607010.61 | J15: 538126.35 | K15: 485150.16 | L15: 6633327.2
